.DS_Store
bio2bel_hgnc/__init__.py
bio2bel_hgnc/__main__.py
bio2bel_hgnc/cli.py
bio2bel_hgnc/constants.py
bio2bel_hgnc/enrich.py
bio2bel_hgnc/gfam_manager.py
bio2bel_hgnc/integrate.py
bio2bel_hgnc/manager.py
bio2bel_hgnc/model_utils.py
bio2bel_hgnc/models.py
bio2bel_hgnc/to_bel.py
bio2bel_hgnc/to_belns.py
bio2bel_hgnc/utils.py
bio2bel_hgnc/web.py
bio2bel_hgnc/wrapper.py
bio2bel_hgnc-0.3.0.dist-info/LICENSE
bio2bel_hgnc-0.3.0.dist-info/METADATA
bio2bel_hgnc-0.3.0.dist-info/WHEEL
bio2bel_hgnc-0.3.0.dist-info/entry_points.txt
bio2bel_hgnc-0.3.0.dist-info/top_level.txt
bio2bel_hgnc-0.3.0.dist-info/RECORD
