Metadata-Version: 2.1
Name: bio2bel-hgnc
Version: 0.3.0
Summary: A package for converting HGNC to BEL
Home-page: https://github.com/bio2bel/hgnc
Author: Charles Tapley Hoyt
Author-email: cthoyt@gmail.com
Maintainer: Charles Tapley Hoyt
Maintainer-email: cthoyt@gmail.com
License: MIT License
Keywords: Biological Expression Language,BEL,Systems Biology,Networks Biology
Platform: UNKNOWN
Classifier: Development Status :: 4 - Beta
Classifier: Environment :: Console
Classifier: Intended Audience :: Developers
Classifier: Intended Audience :: Science/Research
Classifier: License :: OSI Approved :: MIT License
Classifier: Operating System :: OS Independent
Classifier: Programming Language :: Python
Classifier: Programming Language :: Python :: 3.6
Classifier: Programming Language :: Python :: 3.7
Classifier: Topic :: Scientific/Engineering :: Bio-Informatics
Requires-Dist: pybel (<0.15.0,>=0.14.0)
Requires-Dist: bio2bel (<0.4.0,>=0.3.0)
Requires-Dist: tqdm
Requires-Dist: sqlalchemy
Requires-Dist: click
Requires-Dist: pyhgnc
Provides-Extra: docs
Requires-Dist: flask ; extra == 'docs'
Requires-Dist: flask-admin ; extra == 'docs'
Requires-Dist: sphinx ; extra == 'docs'
Requires-Dist: sphinx-rtd-theme ; extra == 'docs'
Requires-Dist: sphinx-click ; extra == 'docs'
Requires-Dist: sphinx-autodoc-typehints ; extra == 'docs'
Provides-Extra: web
Requires-Dist: flask ; extra == 'web'
Requires-Dist: flask-admin ; extra == 'web'
